unicall/__init__.py
unicall/base_transport.py
unicall/data_models.py
unicall/decorators.py
unicall/errors.py
unicall/json_rpc.py
unicall/unicall_class.py
unicall/utils.py
unicall-0.2.0.dist-info/METADATA
unicall-0.2.0.dist-info/WHEEL
unicall-0.2.0.dist-info/licenses/LICENSE.txt
unicall-0.2.0.dist-info/RECORD
