Metadata-Version: 2.3
Name: unicall
Version: 0.2.0
Summary: Easy to use RPC library based on uniserde
Author-email: Jakob Pinterits <jakob.pinterits@gmail.com>
License: Copyright (c) 2023 Jakob Pinterits
Requires-Python: >=3.10
Requires-Dist: imy<0.8,>=0.7
Requires-Dist: uniserde<0.5,>=0.4.0
